at16k/__init__.py
at16k/api/__init__.py
at16k/api/live_speech_to_text.py
at16k/api/speech_to_text.py
at16k/bin/speech_to_text.py
at16k/blocks/transcriber.py
at16k/core/live_inference.py
at16k/core/live_model.py
at16k/core/media.py
at16k/core/microphone.py
at16k/core/model.py
at16k/core/segment.py
at16k/download.py
at16k/utils/text_encoder.py
at16k/utils/tokenizer.py
at16k-0.1.5.dist-info/entry_points.txt
at16k-0.1.5.dist-info/LICENSE.md
at16k-0.1.5.dist-info/WHEEL
at16k-0.1.5.dist-info/METADATA
at16k-0.1.5.dist-info/RECORD
