Metadata-Version: 2.1
Name: at16k
Version: 0.1.5
Summary: at16k is a Python library to perform automatic speech recognition or speech to text conversion.
Home-page: https://github.com/at16k/at16k.git
License: MIT
Keywords: asr, automatic speech recognition, speech-to-text, speech recognition, speech analysis
Author: Mohit Shah
Author-email: mohit@at16k.com
Requires-Python: >=3.6,<4.0
Classifier: License :: OSI Approved :: MIT License
Classifier: Programming Language :: Python :: 3
Classifier: Programming Language :: Python :: 3.6
Classifier: Programming Language :: Python :: 3.7
Requires-Dist: progressbar (>=2.5,<3.0)
Requires-Dist: scipy (>=1.3.3,<2.0.0)
Requires-Dist: sentencepiece (==0.1.82)
Requires-Dist: tensorflow (==1.14)
Project-URL: Repository, https://github.com/at16k/at16k.git
